Metadata-Version: 2.1
Name: odoo-addon-l10n_es_partner
Version: 19.0.1.0.2
Requires-Dist: odoo-addon-base_bank_from_iban==19.0.*
Requires-Dist: odoo==19.0.*
Summary: =?utf-8?q?Adaptaci=C3=B3n_de_los_clientes=2C_proveedores_y_bancos_para_Espa=C3=B1a?=
Home-page: https://github.com/OCA/l10n-spain
License: AGPL-3
Author: ZikZak,Acysos,Tecnativa,Odoo Community Association (OCA)
Author-email: support@odoo-community.org
Classifier: Programming Language :: Python
Classifier: Framework :: Odoo
Classifier: Framework :: Odoo :: 19.0
Classifier: License :: OSI Approved :: GNU Affero General Public License v3
Classifier: Development Status :: 6 - Mature
